iterable_collections/__init__.py
iterable_collections/collection.py
iterable_collections/factory.py
iterable_collections/strategy.py
iterable_collections/utils.py
iterable_collections-0.1.6.data/data/lib/python3.6/site-packages/iterable_collections/collection.pyi
iterable_collections-0.1.6.data/data/lib/python3.6/site-packages/iterable_collections/factory.pyi
iterable_collections-0.1.6.data/data/lib/python3.6/site-packages/iterable_collections/strategy.pyi
iterable_collections-0.1.6.data/data/lib/python3.6/site-packages/iterable_collections/utils.pyi
iterable_collections-0.1.6.dist-info/METADATA
iterable_collections-0.1.6.dist-info/RECORD
iterable_collections-0.1.6.dist-info/WHEEL
iterable_collections-0.1.6.dist-info/top_level.txt
