Metadata-Version: 2.1
Name: iterable-collections
Version: 0.1.6
Summary: A collections pipeline tool for iterable objects with support for iteration with `dict.items`
Home-page: https://github.com/alliefitter/iterable_collections
Author: Allie Fitter
Author-email: fitterj@gmail.com
License: MIT License
Keywords: collection,map,filter,pipeline,linq,scala
Platform: UNKNOWN
Classifier: Programming Language :: Python :: 3
Classifier: License :: OSI Approved :: MIT License
Classifier: Operating System :: OS Independent
